{
  "project_info": {
    "project_number": "195151349103",
    "firebase_url": "https://food-cheetah-default-rtdb.firebaseio.com",
    "project_id": "food-cheetah",
    "storage_bucket": "food-cheetah.appspot.com"
  },
  "client": [
    {
      "client_info": {
        "mobilesdk_app_id": "1:195151349103:android:a4785f0c7fdb76a859149a",
        "android_client_info": {
          "package_name": "com.wonglik.foodcheetah"
        }
      },
      "oauth_client": [
        {
          "client_id": "195151349103-i5ospgpvdeo6ls5sqhhajokhpjmau86h.apps.googleusercontent.com",
          "client_type": 3
        }
      ],
      "api_key": [
        {
          "current_key": "AIzaSyCqK0p0q3OfqYqvHcMA1qVl5PQYMCLM710"
        }
      ],
      "services": {
        "appinvite_service": {
          "other_platform_oauth_client": [
            {
              "client_id": "195151349103-i5ospgpvdeo6ls5sqhhajokhpjmau86h.apps.googleusercontent.com",
              "client_type": 3
            }
          ]
        }
      }
    }
  ],
  "configuration_version": "1"
}